mlflow_artifactory/__init__.py
mlflow_artifactory/store/__init__.py
mlflow_artifactory/store/artifact/__init__.py
mlflow_artifactory/store/artifact/jfrog_artifact_repository.py
mlflow_jfrog_artifactory-0.0.3.dist-info/LICENSE.md
mlflow_jfrog_artifactory-0.0.3.dist-info/METADATA
mlflow_jfrog_artifactory-0.0.3.dist-info/WHEEL
mlflow_jfrog_artifactory-0.0.3.dist-info/entry_points.txt
mlflow_jfrog_artifactory-0.0.3.dist-info/top_level.txt
mlflow_jfrog_artifactory-0.0.3.dist-info/RECORD
