Metadata-Version: 2.1
Name: mlflow-jfrog-artifactory
Version: 0.0.3
Summary: Artifactory plugin for MLflow for Artifact storage
Home-page: UNKNOWN
License: UNKNOWN
Platform: any
Requires-Python: !=3.0.*,!=3.1.*,!=3.2.*,!=3.3.*,<4.0,>=2.7
Requires-Dist: mlflow (>=1.11)
Requires-Dist: rtpy (==1.4.9)
